dicergirl/__init__.py
dicergirl/common/__init__.py
dicergirl/common/const.py
dicergirl/common/messages.py
dicergirl/common/registers.py
dicergirl/common/response.py
dicergirl/common/exceptions/__init__.py
dicergirl/common/exceptions/parseerror.py
dicergirl/common/exceptions/pluginerror.py
dicergirl/handlers/__init__.py
dicergirl/handlers/default.py
dicergirl/handlers/general.py
dicergirl/handlers/on.py
dicergirl/plugins/__init__.py
dicergirl/plugins/operation.py
dicergirl/plugins/parse.py
dicergirl/reply/__init__.py
dicergirl/reply/data.py
dicergirl/reply/init.py
dicergirl/reply/manager.py
dicergirl/reply/registry.py
dicergirl/reply/parsers/__init__.py
dicergirl/reply/parsers/matcher.py
dicergirl/reply/parsers/parser.py
dicergirl/reply/parsers/templates.py
dicergirl/utils/__init__.py
dicergirl/utils/admin.py
dicergirl/utils/blacklist.py
dicergirl/utils/cards.py
dicergirl/utils/charactors.py
dicergirl/utils/dicer.py
dicergirl/utils/docimasy.py
dicergirl/utils/formatters.py
dicergirl/utils/handlers.py
dicergirl/utils/loggers.py
dicergirl/utils/modes.py
dicergirl/utils/operator.py
dicergirl/utils/parser.py
dicergirl/utils/plugins.py
dicergirl/utils/role.py
dicergirl/utils/settings.py
dicergirl/utils/update.py
dicergirl/utils/version.py
dicergirl-3.5.1.dist-info/LICENSE
dicergirl-3.5.1.dist-info/METADATA
dicergirl-3.5.1.dist-info/WHEEL
dicergirl-3.5.1.dist-info/top_level.txt
dicergirl-3.5.1.dist-info/RECORD
