Metadata-Version: 2.1
Name: dicergirl
Version: 3.5.1
Summary: 新一代跨平台开源 TRPG 骰娘框架
Home-page: https://gitee.com/unvisitor/dicer
Author: Night Resurgent <fu050409@163.com>
Author-email: fu050409@163.com
License: Apache-2.0
Project-URL: Bug Tracker, https://gitee.com/unvisitor/dicer/issues
Classifier: Programming Language :: Python :: 3
Classifier: License :: OSI Approved :: Apache Software License
Classifier: Operating System :: OS Independent
Requires-Python: >=3
License-File: LICENSE
Requires-Dist: nonebot2
Requires-Dist: nonebot-adapter-onebot
Requires-Dist: loguru
Requires-Dist: pyyaml
Requires-Dist: openai
Requires-Dist: multilogging
Requires-Dist: psutil
Requires-Dist: nonebot-plugin-apscheduler
Requires-Dist: httpx
Requires-Dist: ruamel.yaml
Requires-Dist: dicergirl-plugin-coc
Requires-Dist: python-Levenshtein
